easydbs/__init__.py
easydbs/dbapi.py
easydbs/exceptions.py
easydbs-1.0.0.dist-info/METADATA
easydbs-1.0.0.dist-info/WHEEL
easydbs-1.0.0.dist-info/top_level.txt
easydbs-1.0.0.dist-info/RECORD
