Metadata-Version: 2.2
Name: easydbs
Version: 1.0.0
Summary: Simple connection manager for sqlalchemy.
Author: Ian Peysson
Project-URL: Homepage, https://github.com/merlendo/easydbs
Project-URL: Issues, https://github.com/merlendo/easydbs/issues
Keywords: database,connection manager,migration
Classifier: Programming Language :: Python :: 3
Classifier: Operating System :: OS Independent
Classifier: License :: OSI Approved :: MIT License
Requires-Python: >=3.8
Requires-Dist: sqlalchemy>=2.0.38
Requires-Dist: sqlmodel>=0.0.22
Provides-Extra: mysql
Requires-Dist: pymysql; extra == "mysql"
Provides-Extra: mariadb
Requires-Dist: pymysql; extra == "mariadb"
Provides-Extra: postgresql
Requires-Dist: psycopg2; extra == "postgresql"
Provides-Extra: mssql
Requires-Dist: pyodbc; extra == "mssql"
Provides-Extra: duckdb
Requires-Dist: duckdb; extra == "duckdb"
Requires-Dist: duckdb_engine; extra == "duckdb"
Provides-Extra: all
Requires-Dist: pymysql; extra == "all"
Requires-Dist: psycopg2; extra == "all"
Requires-Dist: pyodbc; extra == "all"
Requires-Dist: duckdb; extra == "all"
Requires-Dist: duckdb_engine; extra == "all"
